example_config.py
setup.py
test_argparse.py
pfns/base_config.py
pfns/batch_shape_sampler.py
pfns/pfn_bo_bayesmark.py
pfns/run_training_cli.py
pfns/train.py
pfns/training_utils.py
pfns/utils.py
pfns/datasets/__init__.py
pfns/datasets/tabular_datasets.py
pfns/datasets/utils.py
pfns/model/bar_distribution.py
pfns/model/criterions.py
pfns/model/encoders.py
pfns/model/layer.py
pfns/model/layer_norm.py
pfns/model/mlp.py
pfns/model/multi_head_attention.py
pfns/model/save_peak_memory.py
pfns/model/transformer.py
pfns/model/transformer_config.py
pfns/optimizer/__init__.py
pfns/optimizer/adamw_schedulefree.py
pfns/optimizer/config.py
pfns/priors/__init__.py
pfns/priors/batched_discrete_bayes.py
pfns/priors/condition_on_area_of_opt.py
pfns/priors/condition_on_area_of_opt_continuous.py
pfns/priors/data_loading.py
pfns/priors/fast_gp.py
pfns/priors/gp.py
pfns/priors/hebo_prior.py
pfns/priors/hyperparameter_sampling.py
pfns/priors/input_warping.py
pfns/priors/nonmyopic_bo.py
pfns/priors/normalize_with_style.py
pfns/priors/prior.py
pfns/priors/prior_bag.py
pfns/priors/sample_num_features.py
pfns/priors/simple_mlp.py
pfns/priors/utils.py
pfns/priors/formula/__init__.py
pfns/priors/formula/get_batch.py
pfns/priors/formula/ops.py
pfns/priors/formula/trees.py
pfns/priors/formula/utils.py
pfns/scripts/acquisition_functions.py
pfns/scripts/tabpfn_interface.py
pfns/scripts/tabpfn_model_builder.py
pfns/scripts/tabular_metrics.py
pfns/scripts/tune_input_warping.py
tests/model/test_attention.py
tests/model/test_bar_distribution.py
tests/model/test_transformer.py
tests/priors/test_hyperparameter_sampling.py
pfns-0.4.2.dist-info/METADATA
pfns-0.4.2.dist-info/WHEEL
pfns-0.4.2.dist-info/licenses/LICENSE
pfns-0.4.2.dist-info/RECORD
