Metadata-Version: 2.1
Name: pfns
Version: 0.4.2
Summary: PFNs made ready for BO
Project-URL: Homepage, https://github.com/automl/PFNs4BO
Author: Samuel Muller, Matthias Feurer, Noah Hollmann, Frank Hutter
License-File: LICENSE
Classifier: Operating System :: OS Independent
Classifier: Programming Language :: Python :: 3
Requires-Python: >=3.9
Requires-Dist: black==24.4.2
Requires-Dist: configspace>=0.4.21
Requires-Dist: einops>=0.8.1
Requires-Dist: flake8-bugbear>=24.0.0
Requires-Dist: gpytorch>=1.5.0
Requires-Dist: matplotlib>=3.10.1
Requires-Dist: numpy>=1.21.2
Requires-Dist: pre-commit>=3.5.0
Requires-Dist: pytest>=5.4.3
Requires-Dist: pyyaml>=5.4.1
Requires-Dist: requests>=2.23.0
Requires-Dist: ruff-api==0.1.0
Requires-Dist: scikit-learn>=0.24.2
Requires-Dist: stdlibs==2024.1.28
Requires-Dist: tensorboard>=2.20.0
Requires-Dist: torch>=2.2
Requires-Dist: tqdm>=4.62.1
Requires-Dist: usort==1.0.8.post1
Provides-Extra: benchmarks
Requires-Dist: bayesmark>=0.0.8; extra == 'benchmarks'
Provides-Extra: priors
Requires-Dist: botorch; extra == 'priors'
